mcp_dispatch/__init__.py
mcp_dispatch/server.py
vantransTool/__init__.py
vantransTool/_version.py
vantransTool/client.py
vantransTool/config.py
vantranstool-0.1.1.dist-info/METADATA
vantranstool-0.1.1.dist-info/WHEEL
vantranstool-0.1.1.dist-info/entry_points.txt
vantranstool-0.1.1.dist-info/top_level.txt
vantranstool-0.1.1.dist-info/RECORD
