Metadata-Version: 2.4
Name: vantranstool
Version: 0.1.1
Summary: 一个基于MCP协议的运输工具服务，提供批量外部派车功能
Home-page: https://github.com/yourusername/vantransTool
Author: baiyx
Author-email: baiyx <baiyx@example.com>
License: MIT
Requires-Python: >=3.8
Requires-Dist: mcp-client>=0.1.0
Requires-Dist: mcp-server>=0.1.0
Requires-Dist: requests>=2.31.0
Requires-Dist: fastapi>=0.109.0
Requires-Dist: uvicorn>=0.27.0
Dynamic: author
Dynamic: home-page
Dynamic: requires-python
